average_pixels/__init__.py
average_pixels/average_pixels.py
average_pixels/get_images.py
average_pixels/parse_args.py
average_pixels/version.py
average_pixels-1.1.0.dist-info/DESCRIPTION.rst
average_pixels-1.1.0.dist-info/METADATA
average_pixels-1.1.0.dist-info/RECORD
average_pixels-1.1.0.dist-info/WHEEL
average_pixels-1.1.0.dist-info/entry_points.txt
average_pixels-1.1.0.dist-info/metadata.json
average_pixels-1.1.0.dist-info/top_level.txt
